stoch/__init__.py
stoch/version.py
stoch-1.0.0.dist-info/METADATA
stoch-1.0.0.dist-info/WHEEL
stoch-1.0.0.dist-info/top_level.txt
stoch-1.0.0.dist-info/RECORD
