Metadata-Version: 2.1
Name: stoch
Version: 1.0.0
Summary: Stochastic Process
Home-page: http://github.com/zhiqingxiao/stoch/
Author: Zhiqing Xiao
Author-email: xzq.xiaozhiqing@gmail.com
Classifier: Programming Language :: Python
Classifier: Intended Audience :: Science/Research
